{
    "modes": [
        {
            "id": "training_basic",
            "title": "Basic Training: Ten",
            "background": "background1",
            "music": "battle",
            "enemy": "Ten",
            "timeLimit": 99
        },
        {
            "id": "training_basic_2",
            "title": "Basic Training: Shiro",
            "background": "background2",
            "music": "battle",
            "enemy": "shiro",
            "timeLimit": 99
        },
        {
            "id": "training_basic_3",
            "title": "Basic Training: Reika",
            "background": "background3",
            "music": "battle",
            "enemy": "reika",
            "timeLimit": 99
        },
        {
            "id": "training_basic_4",
            "title": "Basic Training: Rei",
            "background": "background4",
            "music": "battle",
            "enemy": "rei",
            "timeLimit": 99
        }
    ]
}
